[{"type":"{{","value":[["pagebanner"],["Pagebanner default.jpg"]]},"\n",{"type":"'''","value":["Achill Island"]}," is the largest island off the ",{"type":"[[","value":[["County Mayo"],["west coast"]]}," of ",{"type":"[[","value":[["Ireland"]]},". It is connected to the mainland by a bridge at Achill Sound.\n\n",{"type":"==","value":["Regions"]},"\n\n",{"type":"==","value":["Cities"]},"\nThe main villages of Achill are (from the west) Dooagh, Pollagh, Keel, Dookinella, The Valley, Bunacurry, Cashel, Dooega, Saula, Ashleam, Dereens, Cloughmore, Achill Sound and Currane.\n\n",{"type":"==","value":["Other destinations"]},"\n\n",{"type":"==","value":["Understand"]},"\nAchill is an island but is connected to the mainland of Ireland by a bridge at Achill Sound. The bridge spans about 100 metres and allows two lanes of traffic to pass onto the island.\n\n",{"type":"==","value":["Talk"]},"\nThey speak traditional Irish as well as English.\n\n",{"type":"==","value":["Get in"]},"\nYou can get to Achill by car or bus. Two buses a day leave from Westport to Achill and back.\n\n",{"type":"==","value":["Get around"]},"\n\n",{"type":"==","value":["See"]},"\n\nAchill has a beautiful little sandy beach - Keel Bay. The view from Menaun Heights towards this bay is spectacular.\n\n",{"type":"==","value":["Do"]},"\nVarious stunning beaches make this a popular holiday location for the locals.\n\n",{"type":"==","value":["Eat"]},"\n",{"type":"*","value":[{"type":"{{","value":[["eat"],["name=Bayside Bistro"],["url=http:\/\/www.baysidebistro.ie"],["email="],["address=Keel"],["lat="],["long="],["directions="],["phone=+353 98 43798"],["tollfree="],["fax="],["hours="],["price="],["content=Family friendly sea food restaurant."]]}]},"\n",{"type":"==","value":["Drink"]},"\n\n",{"type":"==","value":["Stay safe"]},"\n\n",{"type":"==","value":["Go next"]},"\n\n\n",{"type":"{{","value":[["outlineregion"]]},"\n",{"type":"{{","value":[["IsPartOf"],["County Mayo"]]},"\n\n",{"type":"[[","value":[["Wikipedia:Achill Island"]]},"\n\n",{"type":"{{","value":[["geo"],["53.958888888889"],["-10.038888888889"]]}]