[{"type":"{{","value":[["pagebanner"],["Pagebanner default.jpg"]]},"\n",{"type":"'''","value":["Alveston"]}," is a large village situated on the A38 near ",{"type":"[[","value":[["Thornbury"]]},".\n\n",{"type":"==","value":["Understand"]},"\n\n",{"type":"==","value":["Get in"]},"\n",{"type":"*","value":["By car, take the A38 after getting off the M5 motorway either at junction 16 or 14,"]},{"type":"*","value":["By bus, take the Local bus services 309\/310. Operated by First Bus as of 2013, formerly Badgerline."]},"\n",{"type":"==","value":["Get around"]},"\n\n",{"type":"==","value":["See"]},"\n\n",{"type":"==","value":["Do"]},"\n",{"type":"===","value":["Churches"]},"\n",{"type":"*","value":["St Helen's Church."]},{"type":"[[","value":[["File:Alveston-sthelens.jpg"],["right"],["thumb"],["St Helen's ",{"type":"[[","value":[["Church"]]},"."]]},"\n\n",{"type":"==","value":["Buy"]},"\n\n",{"type":"==","value":["Eat"]},"\n\n",{"type":"==","value":["Drink"]},"\n\n",{"type":"==","value":["Sleep"]},"\n\n",{"type":"==","value":["Connect"]},"\n\n",{"type":"==","value":["Go next"]},"\n",{"type":"*","value":[{"type":"[[","value":[["Thornbury"]]}]},{"type":"*","value":[{"type":"[[","value":[["Rudgeway"]]}]},{"type":"*","value":[{"type":"[[","value":[["Olveston"]]}]},"\n",{"type":"{{","value":[["IsPartOf"],["Gloucestershire"]]},"\n",{"type":"{{","value":[["outlinecity"]]},"\n",{"type":"[[","value":[["wikipedia:Alveston"]]},"\n",{"type":"{{","value":[["geo"],["51.58955"],["-2.53179"],["zoom=16"]]}]