[{"type":"{{","value":[["pagebanner"],["Pagebanner default.jpg"]]},"\n",{"type":"'''","value":["Cavendish and Rustico Harbour"]}," is a mostly rural area on the north shore of ",{"type":"[[","value":[["Prince Edward Island"]]},", Canada, and includes the villages of Cavendish, North Rustico, Rusticoville and South Rustico. It is probably best known for its museum and heritage site for Lucy Maud Montgomery, author of the Anne of Green Gables books. There are also a number of accommodation and restaurant options to support visitors to the nearby Prince Edward Island National Park.\n\n",{"type":"==","value":["Get in"]},"\nPEI Highway 6 connects all the villages. It is about a 45 minute drive from ",{"type":"[[","value":[["Charlottetown"]]},".\n\n",{"type":"==","value":["Get around"]},"\n\n",{"type":"==","value":["See"]},"\n",{"type":"[[","value":[["File:Green Gables.jpg"],["thumb"],["right"],["250px"],["The Green Gables farmhouse"]]},"\n",{"type":"*","value":[" ",{"type":"{{","value":[["see"],["name=Green Gables Heritage Place"],["url=http:\/\/www.pc.gc.ca\/eng\/lhn-nhs\/pe\/greengables\/index.aspx"],["email="],["address=Route 6, Cavendish"],["lat="],["long="],["directions="],["phone="],["tollfree="],["fax="],["hours="],["price=$7.80"],["content="]]}]},"\n",{"type":"==","value":["Do"]},"\n",{"type":"*","value":[" ",{"type":"{{","value":[["do"],["name=Green Gables Golf Course"],["alt=Green Gables & Andersons Creek Golf Courses"],["url=http:\/\/httpL\/\/www.greengablesgolf.ca\/"],["email=golf@greengablesgolf.com"],["address=8727 Cavendish Road, Hunter River, PEI"],["lat=46.48943"],["long=-63.38251"],["directions="],["phone=+1 902 963-4653"],["tollfree=+1-888-870-5454"],["fax="],["hours="],["price="],["content=A scenic, ocean-side golf course, Green Gables measures 7000 yards from the back tees."]]}]},"\n",{"type":"==","value":["Buy"]},"\n\n",{"type":"==","value":["Eat"]},"\n\n",{"type":"==","value":["Drink"]},"\n\n",{"type":"==","value":["Sleep"]},"\n\n",{"type":"==","value":["Connect"]},"\n\n",{"type":"==","value":["Go next"]},"\n\n",{"type":"{{","value":[["IsPartOf"],["Prince Edward Island"]]},"\n",{"type":"{{","value":[["outlinecity"]]},"\n",{"type":"{{","value":[["no Wikipedia link"]]},"\n",{"type":"{{","value":[["geo"],["46.459"],["-63.311"],["zoom=12"]]}]