[{"type":"{{","value":[["pagebanner"],["Disambiguation banner.png"]]},"\n__NOTOC__\nThere is more than one place called ",{"type":"'''","value":["Cloverdale"]},":\n\n",{"type":"===","value":[{"type":"[[","value":[["United States"]]}]},"\n\n",{"type":"*","value":[" ",{"type":"[[","value":[["Cloverdale (California)"]]}," - A town in ",{"type":"[[","value":[["California"]]},"."]},"\n",{"type":"===","value":[{"type":"[[","value":[["British Columbia"]]}]},"\n\n",{"type":"*","value":[" ",{"type":"[[","value":[["Cloverdale (British Columbia)"]]}," - A town in ",{"type":"[[","value":[["Surrey (British Columbia)"]]},"."]},"\n",{"type":"{{","value":[["disamb"]]},"\n\n",{"type":"[[","value":[["WikiPedia:Cloverdale"]]}]