[{"type":"{{","value":[["Pagebanner"],["Lumpytrout wikivoyage page banner cactus blossom.jpg"],["box=black"]]},"\n\n",{"type":"'''","value":["Custer Country"]}," is a region of ",{"type":"[[","value":[["Montana"]]},".  It is in the southeast part of the state.  The name comes from the Little Big Horn Battlefield, often called Custer's Last Stand.\n",{"type":"[[","value":[["File:Big horn river canyon.jpg"],["300px"],["thumbnail"],["Big Horn River Canyon"]]},"\n",{"type":"==","value":["Regions"]},"\n\n",{"type":"==","value":["Cities"]},"\n",{"type":"*","value":[" ",{"type":"[[","value":[["Billings"]]}," -the largest city in Montana."]},{"type":"*","value":[" ",{"type":"[[","value":[["Colstrip"]]}]},{"type":"*","value":[" ",{"type":"[[","value":[["Crow Agency"]]}]},{"type":"*","value":[" ",{"type":"[[","value":[["Forsyth"]]}]},{"type":"*","value":[" ",{"type":"[[","value":[["Glendive"]]}]},{"type":"*","value":[" ",{"type":"[[","value":[["Huntley"]]}]},{"type":"*","value":[" ",{"type":"[[","value":[["Miles City"]]}]},"\n",{"type":"==","value":["Other destinations"]},"\n\n",{"type":"==","value":["Understand"]},"\n\n",{"type":"==","value":["Talk"]},"\n\n",{"type":"==","value":["Get in"]},"\n\n",{"type":"==","value":["Get around"]},"\nAs with most of Montana, travel by car is the primary way to get around.  In this rural area there are very few additional options. The larger towns, such as Miles City, do have a taxi cab company.\n\n",{"type":"==","value":["See"]},"\n",{"type":"[[","value":[["File:Schlacht am Little Bighorn River.jpg"],["200px"],["thumbnail"],["The Battle of the Little Big Horn"]]},"\n",{"type":"*","value":[" ",{"type":"{{","value":[["see"],["name=Custer Battlefield Museum"],["alt=All of the locations associated with the Battle of the Little Bighorn, known as Custer's Last Stand"],["url=http:\/\/custermuseum.org\/"],["email="],["address=Garryowen, Montana"],["lat="],["long="],["directions="],["phone =+1 406 638-1876"],["tollfree="],["fax="],["hours=Hours: Summer 8AM to 7PM; 9AM to 5PM"],["price=Price:$5 adults, 12 and under free"],["content="]]}]},"\n",{"type":"===","value":["Itineraries"]},"\n\n",{"type":"==","value":["Do"]},"\n\n",{"type":"==","value":["Eat"]},"\n\n",{"type":"==","value":["Drink"]},"\n\n",{"type":"==","value":["Stay safe"]},"\nDuring the winter, smaller secondary roads are often closed entirely, and even the Interstate can shut down rapidly when the weather turns poor.  Verify weather conditions and road status ",{"type":"[","value":["http:\/\/www.mdt.mt.gov\/travinfo\/map\/mismap_frame.html"]}," before setting out, and travel with emergency supplies.  Unpaved roads are typically impassable for over half the year.\n\n",{"type":"==","value":["Go next"]},"\n\n\n",{"type":"{{","value":[["IsPartOf"],["Montana"]]},"\n",{"type":"{{","value":[["outlineregion"]]},"\n",{"type":"{{","value":[["no Wikipedia link"]]}]