[{"type":"{{","value":[["pagebanner"],["Fall_River_Lake_7x1.png"]]},"\n\n",{"type":"'''","value":["Fall River Mills"]}," is a town in the ",{"type":"[[","value":[["Shasta Cascades"]]}," region of ",{"type":"[[","value":[["California"]]},".\n\n",{"type":"==","value":["Get in"]},"\nSmall private plane airport.\n\nThe best way to go is by car.\n\n",{"type":"===","value":["By car"]},"\n\nFrom Redding or Eureka, go east on CA-299 E until you get to Fall River Mills, which is about 69 mi. from Redding and 218 mi. from Eureka.\n\n",{"type":"==","value":["Get around"]},"\n\nThe main way to get around is by car.\n\n",{"type":"==","value":["See"]},"\n\n\n",{"type":"[[","value":[["File:Fall River Mills Round Barn.JPG"],["thumb"],["The Round Barn at Fort Crook Museum"]]},"\n\n",{"type":"*","value":[" ",{"type":"{{","value":[["see"],["name=Fort Crook Museum"],["url="],["email="],["address=43030 Fort Crook Avenue, Fall River Mills, CA"],["lat="],["long="],["directions="],["phone = +1 530  336-5110"],["tollfree="],["fax="],["hours=May 1 - Oct 31: Tu-Su 12pm-4pm"],["price=Free"],["content= You will see the Round Barn at the corner of HW 299 at Glenburn Road. Covers the history of the Fall River Valley."]]}]},"\n",{"type":"==","value":["Do"]},"\n\nThis place is heaven for boaters and fishermen.\n\n",{"type":"===","value":["Fishing\/Boating"]},"\n\n",{"type":"*","value":[" ",{"type":"'''","value":["Fall River."]}," The best Fall River trout fishing is to the north west of the valley. Guides can be hired locally. Fall River has a few access points for private boating. Abundant wanter from underground springs in the north end of the valley keeps Fall River flowing year round. The river meanders for 16 miles through the valley and terminates to the south at Pit 1 Diversion Dam where the water drops hundreds of feet in elevation through twin massive pipes bored through Saddle Mountain to power the hydroelectric Pit 1 Powerhouse, and then joins the Pit River."]},{"type":"*","value":[" ",{"type":"'''","value":["Pit River."]}," Trout fishing the Pit River is what most people come here for.  Fly fishing is usually best here.  Be sure to check with both the fishing reports and the locals."]},"\n",{"type":"==","value":["Buy"]},"\n\nThere are no major shopping centers in Fall River Mills.  If you are fishing, it might be a good thing to buy some fishing equipment if you're low on it.\n\n",{"type":"==","value":["Eat"]},"\n\n",{"type":"<","value":["b",["Fall River Hotel and Restaurant"]]},": 24860 Main St., (530) 336-5550\n\nNOTE: The above entry is also listed in the ",{"type":"<","value":["b",["Sleep"]]}," section of this page.\n\n",{"type":"<","value":["b",["Uptown Pizza"]]},": 43131 Main St., (530) 336-7177\n\n",{"type":"<","value":["b",["Slam Dunk Pizza"]]},": 43218 State Highway 299 E., (530) 336-5660\n\n",{"type":"==","value":["Drink"]},"\n\n",{"type":"==","value":["Sleep"]},"\n\n",{"type":"<","value":["b",["Fall River Hotel and Restaurant"]]},": 24860 Main St., (530) 336-5550\n\nNOTE: The above entry is also listed in the ",{"type":"<","value":["b",["Eat"]]}," section of this page.\n\n",{"type":"==","value":["Go next"]},"\n",{"type":"{{","value":[["routebox"],["image1=California 299.svg"],["imagesize1=22"],["directionl1=W"],["majorl1=",{"type":"[[","value":[["Redding"]]}],["minorl1=",{"type":"[[","value":[["Burney"]]}],["directionr1=E"],["majorr1=",{"type":"[[","value":[["Alturas"]]}],["minorr1=",{"type":"[[","value":[["McArthur"]]}]]},"\n\n",{"type":"{{","value":[["geo"],["41.00472"],["-121.43833"]]},"\n\n",{"type":"{{","value":[["isPartOf"],["Shasta County"]]},"\n",{"type":"{{","value":[["outlinecity"]]},"\n\n",{"type":"[[","value":[["Wikipedia:Fall River Mills, California"]]},"\n\n",{"type":"[[","value":[["Dmoz:Regional\/North_America\/United_States\/California\/Localities\/F\/Fall_River_Mills\/"]]},"\n\n",{"type":"[[","value":[["Commons:Category:Fall River Mills"]]}]