[{"type":"{{","value":[["pagebanner"],["Pagebanner default.jpg"]]},"\n",{"type":"[[","value":[["Image:Alfl alibates 20060726164737.jpg"],["thumb"],["325px"],["Alibates Flint Quarry"]]},"\n",{"type":"'''","value":["Fritch"]},"  is a city in the ",{"type":"[[","value":[["High Plains"]]}," region of ",{"type":"[[","value":[["Texas"]]},".\n\n",{"type":"==","value":["Get in"]},"\nThe town is located 30 miles north-northeast of ",{"type":"[[","value":[["Amarillo"]]}," on TX Highway 136.  It is also 10 miles west of ",{"type":"[[","value":[["Borger"]]}," on that same highway.\n\n",{"type":"==","value":["Get around"]},"\n\n",{"type":"==","value":["See"]},"\n",{"type":"*","value":[" ",{"type":"'''","value":["Alibates Flint Quarry National Monument"]},", Cas Johnson Road (",{"type":"''","value":["off Texas 136 seven miles southwest of town"]},"), 806 857 3151, ",{"type":"[","value":["http:\/\/www.nps.gov\/alfl\/"]},". Beginning around 13,000 years ago, American Indians collected high-quality flint here for weapon and tool-making. Alibates Flint was traded across the continent long before the Europeans made their appearance. The park has over 700 quarry sites. Free tours are available by reservation only at 10am and 2pm daily."]},{"type":"*","value":[" ",{"type":"'''","value":["Lake Meredith National Recreation Area"]},", headquarters at 419 E. Broadway.  This man-made reservoir provides drinking water for 11 nearby cities and is a popular spot for boating and fishing. The surrounding lands have canyons of up to 200 feet and provide ample opportunities for hiking and observing wildlife."]},{"type":"*","value":[" ",{"type":"'''","value":["Lake Meredith Aquatic and Wildlife Museum"]}," has dioramas displaying the local landscape and wildlife of the area, a large freshwater aquarium that includes several species of fish found in Lake Meredith, and a new display on Playa Lakes."]},{"type":"==","value":["Do"]},"\nCamping, fishing, hiking, hunting, boating and water sports are all popular outdoor activities in and around the Lake Meredith National Recreation Area.  \n\n",{"type":"==","value":["Buy"]},"\nOther than a few shops serving locals, there is not a lot of shopping in town.  \n\n",{"type":"==","value":["Eat"]},"\nSeveral restaurants line Broadway (TX 136) through town.\n\n",{"type":"==","value":["Drink"]},"\nThe town itself is dry but there are packaged liquor stores and some bars on the outskirts of the city.  Follow the signs!\n\n",{"type":"==","value":["Sleep"]},"\nOptions in Fritch are few, though Lake Meredith offers camp sites. More lodging options are available in neighboring ",{"type":"[[","value":[["Borger"]]}," or down the road in ",{"type":"[[","value":[["Amarillo"]]},".\n",{"type":"*","value":[" ",{"type":"'''","value":["Lone Star Inn"]},", 205 E Broadway, 806 857 3191."]},"\n",{"type":"==","value":["Connect"]},"\n\n",{"type":"==","value":["Go next"]},"\n",{"type":"{{","value":[["routebox-1"],["image1=Texas 136.svg"],["imagesize1=22"],["directionl1=W"],["majorl1=END"],["minorl1=",{"type":"[[","value":[["Amarillo"]]}],["directionr1=N"],["majorr1=",{"type":"[[","value":[["Guymon"]]}],["minorr1=",{"type":"[[","value":[["Borger"]]}]]},"\n\n",{"type":"{{","value":[["geo"],["35.63972"],["-101.60333"]]},"\n\n",{"type":"{{","value":[["IsPartOf"],["High Plains"]]},"\n",{"type":"{{","value":[["outlinecity"]]},"\n\n\n",{"type":"[[","value":[["Wikipedia:Fritch, Texas"]]},"\n\n",{"type":"[[","value":[["Dmoz:Regional\/North_America\/United_States\/Texas\/Localities\/F\/Fritch\/"]]}]