[{"type":"{{","value":[["pagebanner"],["Pagebanner default.jpg"]]},"\n",{"type":"'''","value":[{"type":"[","value":["http:\/\/turizem.kamnik.si\/ Škofja Loka"]}]}," is a town in ",{"type":"[[","value":[["Central Slovenia"]]},".\n\n",{"type":"==","value":["Get in"]},"\n\n",{"type":"===","value":["By plane"]},"\nŠkofja Loka is 20 km away from ",{"type":"[[","value":[["Ljubljana"]]},"'s Brnik Airport.  A taxi costs around €60.\n\n",{"type":"*","value":[" ",{"type":"'''","value":["Airport Taxi ( Brnik ) Jože Pučnik Ljubljana-Slovenia"]},",+386 41 670216,taxibrnik@gmail.com,",{"type":"[","value":["http:\/\/www.taxi-domzale.tk"]},"."]},"\n",{"type":"===","value":["By train"]},"\n\n",{"type":"===","value":["By bus"]},"\n",{"type":"'''","value":[{"type":"[","value":["http:\/\/www.kam-bus.si\/ Kam-Bus"]}]}," runs frequent services from ",{"type":"[[","value":[["Ljubljana"]]}," (€3) and some limited direct services to other points nearby.  The bus station is very centrally located at the edge of the old town, and there's a map to orient yourself as you exit.  On weekdays, buses leave every 15-30 minutes from 5 AM until 11 PM and take just under an hour.  On weekends, services are reduced to once per hour.\n\n",{"type":"==","value":["Get around"]},"\nŠkofja Loka is easily covered on foot.\n\n",{"type":"==","value":["See"]},"\nŠkofja Loka is medieval town and very important for Slovenes. One of Slovenia's most famous books was being setted in Škofja Loka, Ivan Tavčar's ",{"type":"''","value":["Visoška hronika"]},".\n\n",{"type":"==","value":["Do"]},"\n\n",{"type":"*","value":[" Veronikina pot (",{"type":"''","value":["Veronika's Path"]},")"]},{"type":"*","value":[" Škofjeloški pasijon (",{"type":"''","value":["The Škofja Loka passion"]},"), it is only displayed on few years"]},"\n",{"type":"==","value":["Buy"]},"\n\nIn centre of Škofja Loka there's a lot of shops with clothes, souvenirs and books.\n\n",{"type":"==","value":["Eat"]},"\n\n",{"type":"==","value":["Drink"]},"\nThere are few cafés in city centre but the most beautiful of all is ",{"type":"'''","value":[{"type":"[","value":["http:\/\/www.skofja-loka.com\/128\/section.aspx\/135\/kavarna-in-slaiarna-homan Homan"]}]},", where you can drink a cup of coffee under a big 100 year old linden tree.\n\n",{"type":"==","value":["Sleep"]},"\n\n",{"type":"==","value":["Connect"]},"\n\n",{"type":"==","value":["Go next"]},"\n\n",{"type":"*","value":[" Lubnik"]},{"type":"*","value":[" Poljanska dolina (Visoko, Žiri)"]},{"type":"*","value":[" Selška dolina (Železniki, Zali log)"]},"\n",{"type":"{{","value":[["outlinecity"]]},"\n\n\n",{"type":"{{","value":[["geo"],["46.1667"],["14.3000"]]},"\n\n",{"type":"{{","value":[["isPartOf"],["Central Slovenia"]]},"\n\n",{"type":"[[","value":[["WikiPedia:Škofja Loka"]]},"\n\n",{"type":"[[","value":[["Commons:Škofja Loka"]]}]