[{"type":"{{","value":[["pagebanner"],["Australia-oceania default banner.jpg"]]},"\n",{"type":"'''","value":["Tawonga"]}," is the original settlement in the upper Kiewa River Valley in the ",{"type":"[[","value":[["High Country (Victoria)"],["Victorian High Country"]]},". Close by is the town of Mount Beauty, a \"model\" town built as a construction village for the Kiewa Hydro-electric Scheme of the 1940's.\n\n",{"type":"==","value":["Understand"]},"\n\n",{"type":"==","value":["Get in"]},"\n\n",{"type":"==","value":["Get around"]},"\n\n",{"type":"==","value":["See"]},"\n\n",{"type":"==","value":["Do"]},"\n\n",{"type":"==","value":["Buy"]},"\n\n",{"type":"==","value":["Eat"]},"\n\n",{"type":"==","value":["Drink"]},"\n\n",{"type":"==","value":["Sleep"]},"\n\n",{"type":"==","value":["Connect"]},"\n\n",{"type":"==","value":["Go next"]},"\n\n",{"type":"{{","value":[["geo"],["-36.6333"],["147.1000"]]},"\n\n",{"type":"{{","value":[["IsPartOf"],["High Country (Victoria)"]]},"\n",{"type":"{{","value":[["outlinecity"]]},"\n\n\n",{"type":"[[","value":[["WikiPedia:Tawonga, Victoria"]]},"\n\n",{"type":"[[","value":[["Dmoz:Regional\/Oceania\/Australia\/Victoria\/Localities\/T\/Tawonga\/"]]}]