[{"type":"{{","value":[["pagebanner"],["Disambiguation banner.png"]]},"\n__NOTOC__\nThere is more than one place called ",{"type":"'''","value":["Depew"]},":\n\n",{"type":"===","value":[{"type":"[[","value":[["United States of America"]]}]},"\n",{"type":"*","value":[{"type":"[[","value":[["Depew (Oklahoma)"]]}," — A town in ",{"type":"[[","value":[["Oklahoma"]]}]},{"type":"*","value":["Depew (New York) — A village in ",{"type":"[[","value":[["New York (state)"],["New York"]]}," split between the towns of ",{"type":"[[","value":[["Cheektowaga"]]}," and ",{"type":"[[","value":[["Lancaster (New York)"],["Lancaster"]]}]},"\n",{"type":"{{","value":[["disamb"]]},"\n",{"type":"[[","value":[["Wikipedia:Depew"]]}]