[{"type":"{{","value":[["pagebanner"],["Pagebanner default.jpg"],["pgname=Grosseto"]]},"\n",{"type":"'''","value":["Grosseto"]}," is a Province of the ",{"type":"[[","value":[["Tuscany"]]}," Region of ",{"type":"[[","value":[["Italy"]]},".\n\n",{"type":"==","value":["Cities"]},"\n",{"type":"*","value":[{"type":"[[","value":[["Grosseto"]]}," – Capital of the Province"]},{"type":"*","value":[{"type":"[[","value":[["Arcidosso"]]}]},{"type":"*","value":[{"type":"[[","value":[["Pitigliano"]]}]},{"type":"*","value":[{"type":"[[","value":[["Porto Ercole"]]}]},{"type":"*","value":[{"type":"[[","value":[["Porto Santo Stefano"]]}]},{"type":"*","value":[{"type":"[[","value":[["Talamone"]]}]},"\n",{"type":"==","value":["Other destinations"]},"\n",{"type":"*","value":[{"type":"[[","value":[["Maremma"]]}," - A region including parts of Livorno, Grosseto and Viterbo."]},{"type":"*","value":[{"type":"[[","value":[["Giglio"]]}," - An island."]},"\n",{"type":"==","value":["Understand"]},"\n\n",{"type":"==","value":["Talk"]},"\n\n",{"type":"==","value":["Get in"]},"\n\n",{"type":"==","value":["Get around"]},"\n\n",{"type":"==","value":["See"]},"\n\n",{"type":"===","value":[" Spas "]},"\n\n",{"type":"*","value":[" ",{"type":"{{","value":[["see"],["name=Casal di Pari's spa"],["alt="],["url=http:\/\/www.civitella-paganico.it\/en\/turismo\/frazioni\/casaldipari"],["email="],["address="],["lat="],["long="],["directions="],["phone="],["tollfree="],["fax="],["hours="],["price="],["content=Casale, also known as Casal di Pari because of its proximity to the older village of Pari, is located on a hill at 470 metres. It was another of the small centres of the Ardengheschi family that later came under the control of Siena. Casale is famous for its spas."]]}]},"\n",{"type":"*","value":[" ",{"type":"{{","value":[["see"],["name=Pitigliano's spa"],["alt="],["url=http:\/\/www.termedipitigliano.eu\/"],["email="],["address="],["lat="],["long="],["directions="],["phone="],["tollfree="],["fax="],["hours="],["price="],["content=the spa of Pitigliano is located in the Maremma, a land of fascinating and significant cultural content."]]}]},"\n",{"type":"*","value":[" ",{"type":"{{","value":[["see"],["name=Saturnia's spa"],["alt="],["url=http:\/\/www.termedisaturnia.it\/it\/"],["email="],["address="],["lat="],["long="],["directions="],["phone="],["tollfree="],["fax="],["hours="],["price="],["content=Saturnia's spa is in the town of Manciano, an oasis of comfort and relax in Tuscany near villages rich of history."]]}]},"\n",{"type":"*","value":[" ",{"type":"{{","value":[["see"],["name=Argentario's spa"],["alt="],["url=http:\/\/www.argentariogolfresortspa.it\/en\/spa"],["email="],["address="],["lat="],["long="],["directions="],["phone="],["tollfree="],["fax="],["hours="],["price="],["content=A 2700 m² spa that mixes modern and retro features. Located between the harbours of fashionable Porto Ercole and Porto Santo Stefano in the Argentario Promontory."]]}]},"\n",{"type":"===","value":["Itineraries"]},"\n\n",{"type":"==","value":["Do"]},"\nThe cascades of Saturnia is a must to visit. The unique geological formation is a great place to relax after a busy schedule. The thermal water runs through a number of natural pools where you can just sit and enjoy.\n\n",{"type":"==","value":["Eat"]},"\n\n",{"type":"==","value":["Drink"]},"\n\n",{"type":"==","value":["Stay safe"]},"\n\n",{"type":"==","value":["Go next"]},"\n\n\n",{"type":"{{","value":[["IsPartOf"],["Tuscany"]]},"\n",{"type":"{{","value":[["outlineregion"]]},"\n",{"type":"{{","value":[["no Wikipedia link"]]}]