[{"type":"{{","value":[["pagebanner"],["Disambiguation banner.png"]]},"\n__NOTOC__\nThere is more than one place called ",{"type":"'''","value":["Nanao"]},":\n\n",{"type":"===","value":[{"type":"[[","value":[["Japan"]]}]},"\n\n",{"type":"*","value":[" ",{"type":"[[","value":[["Nanao (Japan)"]]}," - A town on the ",{"type":"[[","value":[["Noto Peninsula"]]}," of ",{"type":"[[","value":[["Ishikawa"]]},"."]},"\n",{"type":"===","value":[{"type":"[[","value":[["Taiwan"]]}]},"\n\n",{"type":"*","value":[" ",{"type":"[[","value":[["Nanao (Taiwan)"]]}," - An aboriginal village in ",{"type":"[[","value":[["Ilan County"]]},"."]},"\n",{"type":"{{","value":[["disamb"]]}]